ANNOUNCE.txt
LICENSE.txt
MANIFEST.in
README
README.rst
THANKS.txt
setup.cfg
setup.py
sp.py
sp.egg-info/PKG-INFO
sp.egg-info/SOURCES.txt
sp.egg-info/dependency_links.txt
sp.egg-info/entry_points.txt
sp.egg-info/top_level.txt