Metadata-Version: 1.0
Name: sp
Version: 1.1.0
Summary: Quickly find out which directories / files are hogging your disk space.
Home-page: http://github.com/pthrasher/sp
Author: Philip Thrasher
Author-email: philipthrasher@gmail.com
License: Unlicense
Platform: UNKNOWN
Classifier: License :: Public Domain
Classifier: Development Status :: 5 - Production/Stable
Classifier: Environment :: Console
Classifier: Intended Audience :: System Administrators
Classifier: Operating System :: OS Independent
Classifier: Programming Language :: Python
Classifier: Topic :: Utilities
